connpass/__init__.py
connpass/client.py
connpass/constants.py
connpass/py.typed
connpass/core/__init__.py
connpass/core/request_handler.py
connpass/models/__init__.py
connpass/models/event.py
connpass/models/presentation.py
connpass-0.2.0.dist-info/METADATA
connpass-0.2.0.dist-info/WHEEL
connpass-0.2.0.dist-info/RECORD
