Metadata-Version: 2.4
Name: connpass
Version: 0.2.0
Summary: Python用connpass API v2クライアント
Project-URL: Repository, https://github.com/ryohidaka/connpass-py.git
Project-URL: Bug Tracker, https://github.com/ryohidaka/connpass-py/issues
Author-email: ryohidaka <39184410+ryohidaka@users.noreply.github.com>
License-Expression: MIT
Keywords: api,api-client,connpass,connpass-api
Requires-Python: >=3.12.2
Requires-Dist: pydantic>=2.11.5
Requires-Dist: requests>=2.32.3
